panda_gym/__init__.py
panda_gym/pybullet.py
panda_gym/utils.py
panda_gym/version.txt
panda_gym/assets/__init__.py
panda_gym/envs/__init__.py
panda_gym/envs/core.py
panda_gym/envs/panda_tasks.py
panda_gym/envs/robots/__init__.py
panda_gym/envs/robots/panda.py
panda_gym/envs/tasks/__init__.py
panda_gym/envs/tasks/flip.py
panda_gym/envs/tasks/pick_and_place.py
panda_gym/envs/tasks/push.py
panda_gym/envs/tasks/reach.py
panda_gym/envs/tasks/slide.py
panda_gym/envs/tasks/stack.py
panda_gym-3.0.7.dist-info/LICENSE
panda_gym-3.0.7.dist-info/METADATA
panda_gym-3.0.7.dist-info/WHEEL
panda_gym-3.0.7.dist-info/top_level.txt
panda_gym-3.0.7.dist-info/RECORD
