Metadata-Version: 2.1
Name: panda-gym
Version: 3.0.7
Summary: Set of robotic environments based on PyBullet physics engine and gymnasium.
Home-page: https://github.com/qgallouedec/panda-gym
Author: Quentin GALLOUÉDEC
Author-email: gallouedec.quentin@gmail.com
Classifier: License :: OSI Approved :: MIT License
Classifier: Programming Language :: Python :: 3.7
Classifier: Programming Language :: Python :: 3.8
Classifier: Programming Language :: Python :: 3.9
Classifier: Programming Language :: Python :: 3.10
License-File: LICENSE
Requires-Dist: gymnasium (>=0.26)
Requires-Dist: pybullet
Requires-Dist: numpy
Requires-Dist: scipy
Provides-Extra: develop
Requires-Dist: pytest-cov ; extra == 'develop'
Requires-Dist: black ; extra == 'develop'
Requires-Dist: isort ; extra == 'develop'
Requires-Dist: pytype ; extra == 'develop'
Requires-Dist: sphinx ; extra == 'develop'
Requires-Dist: sphinx-rtd-theme ; extra == 'develop'
